MANIFEST.in
VERSION
setup.py
aegisx.backends.google.egg-info/PKG-INFO
aegisx.backends.google.egg-info/SOURCES.txt
aegisx.backends.google.egg-info/dependency_links.txt
aegisx.backends.google.egg-info/requires.txt
aegisx.backends.google.egg-info/top_level.txt
aegisx/backends/google/package.json
aegisx/backends/google/datastore/__init__.py
aegisx/backends/google/datastore/_cursor.py
aegisx/backends/google/datastore/_storage.py
aegisx/backends/google/datastore/protocols/__init__.py
aegisx/backends/google/datastore/protocols/idatastorecursor.py
aegisx/backends/google/datastore/protocols/idatastoreentity.py
aegisx/backends/google/datastore/protocols/idatastorekey.py
aegisx/backends/google/datastore/protocols/idatastorequery.py
aegisx/backends/google/datastore/protocols/idatastoretransaction.py
aegisx/backends/google/oauth/__init__.py
aegisx/backends/google/oauth/_clientrepository.py